setup.py
plaza_service/__init__.py
plaza_service/blocks.py
plaza_service/protocol.py
plaza_service/registration.py
plaza_service/service.py
plaza_service/service_configuration.py
plaza_service.egg-info/PKG-INFO
plaza_service.egg-info/SOURCES.txt
plaza_service.egg-info/dependency_links.txt
plaza_service.egg-info/not-zip-safe
plaza_service.egg-info/requires.txt
plaza_service.egg-info/top_level.txt