Metadata-Version: 1.1
Name: plaza-service
Version: 0.0.2
Summary: Helper to build plaza services.
Home-page: https://gitlab.com/plaza-project/bridges/python-plaza-lib
Author: kenkeiras
Author-email: kenkeiras@codigoparallevar.com
License: Apache License 2.0
Platform: UNKNOWN
Classifier: Programming Language :: Python :: 3
Classifier: License :: OSI Approved :: Apache Software License
Classifier: Operating System :: OS Independent
Classifier: Development Status :: 1 - Planning
Classifier: Intended Audience :: Developers
